[
  {
    "id": 0,
    "Name": "Saut de peinture",
    "Description": "Cet objet permet de faire une explosion de peinture.",
    "Types": "commun",
    "Begining price": 50,
    "Nb unit per packs": 5,
    "Nb packs sold": 3,
    "Activation time": 0,
    "Speed boost": 0,
    "Explosion boost": 0,
    "Nb lifes added": 0,
    "File": "0.png"
  },
  {
    "id": 1,
    "Name": "Pigment de peinture vert",
    "Description": "Augmente la vitesse de déplacement de 50% pendant 5 secondes",
    "Types": "commun",
    "Begining price": 30,
    "Nb unit per packs": 6,
    "Nb packs sold": 2,
    "Activation time": 5,
    "Speed boost": 50,
    "Explosion boost": 0,
    "Nb lifes added": 0,
    "File": "1.png"
  },
  {
    "id": 2,
    "Name": "Pigment de peinture rouge",
    "Description": "Augmente la puissance de la prochaine explosion de peinture de 30%",
    "Types": "commun",
    "Begining price": 40,
    "Nb unit per packs": 4,
    "Nb packs sold": 3,
    "Activation time": 0,
    "Speed boost": 0,
    "Explosion boost": 30,
    "Nb lifes added": 0,
    "File": "2.png"
  },
  {
    "id": 3,
    "Name": "Pot de peinture verte",
    "Description": "Augmente la vitesse de déplacement de 50% définitivement",
    "Types": "rare",
    "Begining price": 90,
    "Nb unit per packs": 1,
    "Nb packs sold": 1,
    "Activation time": 0,
    "Speed boost": 50,
    "Explosion boost": 0,
    "Nb lifes added": 0,
    "File": "3.png"
  },
  {
    "id": 4,
    "Name": "Pot de peinture violet",
    "Description": "Octroi une vie supplémentaire",
    "Types": "ultra rare",
    "Begining price": 150,
    "Nb unit per packs": 1,
    "Nb packs sold": 1,
    "Activation time": 0,
    "Speed boost": 0,
    "Explosion boost": 0,
    "Nb lifes added": 1,
    "File": "4.png"
  },
  {
    "id": 5,
    "Name": "Pot de peinture rouge",
    "Description": "Augmente la puissance de l’explosion de peinture définitivement 50%",
    "Types": "rare",
    "Begining price": 100,
    "Nb unit per packs": 1,
    "Nb packs sold": 1,
    "Activation time": 0,
    "Speed boost": 0,
    "Explosion boost": 50,
    "Nb lifes added": 0,
    "File": "5.png"
  },
  {
    "id": 6,
    "Name": "Pinceau",
    "Description": "Cet objet permet de multiplier par 2 le nombre de points obtenus grâce au dash. Plus tu en as plus le niveau augmente",
    "Types": "ultra rare",
    "Begining price": 600,
    "Nb unit per packs": 1,
    "Nb packs sold": 1,
    "Activation time": 0,
    "Speed boost": 0,
    "Explosion boost": 0,
    "Nb lifes added": 0,
    "File": "6.png"
  }
]